hearth/__init__.py
hearth/_collate.py
hearth/_config.py
hearth/_file_utils.py
hearth/_internals.py
hearth/_multihead.py
hearth/activations.py
hearth/containers.py
hearth/events.py
hearth/grad.py
hearth/loop.py
hearth/losses.py
hearth/optimizers.py
hearth/py.typed
hearth/callbacks/__init__.py
hearth/callbacks/base.py
hearth/callbacks/checkpoints.py
hearth/callbacks/finetuner.py
hearth/callbacks/grad_clipping.py
hearth/callbacks/history.py
hearth/callbacks/learning_rate.py
hearth/callbacks/logging.py
hearth/callbacks/monitors.py
hearth/callbacks/stopping.py
hearth/callbacks/utils.py
hearth/data/__init__.py
hearth/data/datasets.py
hearth/data/samplers.py
hearth/data/transforms.py
hearth/metrics/__init__.py
hearth/metrics/_utils.py
hearth/metrics/base.py
hearth/metrics/functional.py
hearth/metrics/metrics.py
hearth/metrics/mixins.py
hearth/metrics/wrappers.py
hearth/modules/__init__.py
hearth/modules/attention.py
hearth/modules/base.py
hearth/modules/embeddings.py
hearth/modules/normalization.py
hearth/modules/pooling.py
hearth/modules/transformer.py
hearth/modules/wrappers.py
hearth/text/__init__.py
hearth/text/tokenizers.py
hearth/text/utils.py
hearth/vision/__init__.py
hearth/vision/datasets.py
hearth/vision/ops.py
hearth/vision/transforms.py
hearth/vision/utils.py
hearth-0.5.0.dist-info/AUTHORS.md
hearth-0.5.0.dist-info/LICENSE
hearth-0.5.0.dist-info/METADATA
hearth-0.5.0.dist-info/WHEEL
hearth-0.5.0.dist-info/top_level.txt
hearth-0.5.0.dist-info/RECORD
