Metadata-Version: 2.1
Name: hearth
Version: 0.5.0
Summary: a collection tools and extensions for working with pytorch
Home-page: https://github.com/leaprovenzano/hearth
Author: Lea Provenzano
Author-email: leaprovenzano@gmail.com
License: MIT license
Keywords: hearth
Platform: UNKNOWN
Classifier: Development Status :: 2 - Pre-Alpha
Classifier: Intended Audience :: Developers
Classifier: License :: OSI Approved :: MIT License
Classifier: Natural Language :: English
Classifier: Programming Language :: Python :: 3
Classifier: Programming Language :: Python :: 3.7
Classifier: Programming Language :: Python :: 3.8
Classifier: Programming Language :: Python :: 3.9
Classifier: Programming Language :: Python :: 3 :: Only
License-File: LICENSE
License-File: AUTHORS.md
Requires-Dist: torch
Requires-Dist: numpy
Requires-Dist: more-itertools
Requires-Dist: collectionish (>=0.5.0)
Requires-Dist: torchvision
Requires-Dist: matplotlib
